mva_pipeline/__init__.py
mva_pipeline/builder.py
mva_pipeline/cli.py
mva_pipeline/config.yaml
mva_pipeline/llm_filter.py
mva_pipeline/pipeline.py
mva_pipeline/redis_manager.py
mva_pipeline/state.py
mva_pipeline/synth.py
mva_pipeline/tools.py
mva_pipeline/analysis/__init__.py
mva_pipeline/analysis/anomaly.py
mva_pipeline/analysis/pca_yield.py
mva_pipeline/analysis/root_cause.py
mva_pipeline/analysis/unified_importance.py
mva_pipeline/db/__init__.py
mva_pipeline/db/connector.py
mva_pipeline/db/extractor.py
mva_pipeline/db/introspect.py
mva_pipeline/db/kubectl_connector.py
mva_pipeline/utils/__init__.py
mva_pipeline/utils/fingerprint.py
litewave_ml_models_yield_data_analysis-0.0.12.dist-info/METADATA
litewave_ml_models_yield_data_analysis-0.0.12.dist-info/WHEEL
litewave_ml_models_yield_data_analysis-0.0.12.dist-info/entry_points.txt
litewave_ml_models_yield_data_analysis-0.0.12.dist-info/top_level.txt
litewave_ml_models_yield_data_analysis-0.0.12.dist-info/RECORD
