Metadata-Version: 2.4
Name: litewave-ml-models-yield-data-analysis
Version: 0.0.12
Summary: Multivariate analytics pipeline for pharmaceutical manufacturing yield optimization
Home-page: https://github.com/aiorch/litewave-ml-models/tree/main/yield_data_analysis
Author: LitewaveAI
Author-email: LitewaveAI <yash@litewave.ai>
Maintainer-email: LitewaveAI <yash@litewave.ai>
License: MIT
Project-URL: Homepage, https://github.com/aiorch/litewave-ml-models/tree/main/yield_data_analysis
Project-URL: Documentation, https://github.com/aiorch/litewave-ml-models/blob/main/yield_data_analysis/README.md
Project-URL: Repository, https://github.com/aiorch/litewave-ml-models/tree/main/yield_data_analysis
Project-URL: Bug Tracker, https://github.com/aiorch/litewave-ml-models/tree/main/yield_data_analysis/issues
Keywords: manufacturing,analytics,pca,shap,anomaly-detection,yield-optimization,pharmaceutical
Classifier: Development Status :: 4 - Beta
Classifier: Intended Audience :: Science/Research
Classifier: Intended Audience :: Manufacturing
Classifier: Topic :: Scientific/Engineering :: Artificial Intelligence
Classifier: Topic :: Scientific/Engineering :: Chemistry
Classifier: License :: OSI Approved :: MIT License
Classifier: Programming Language :: Python :: 3
Classifier: Programming Language :: Python :: 3.8
Classifier: Programming Language :: Python :: 3.9
Classifier: Programming Language :: Python :: 3.10
Classifier: Programming Language :: Python :: 3.11
Classifier: Programming Language :: Python :: 3.12
Requires-Python: >=3.8
Requires-Dist: pandas>=2.0
Requires-Dist: numpy>=1.24
Requires-Dist: scikit-learn>=1.3
Requires-Dist: lightgbm>=4.1
Requires-Dist: shap>=0.43
Requires-Dist: pyod>=1.1
Requires-Dist: dtw-python>=1.4
Requires-Dist: tqdm>=4.66
Requires-Dist: matplotlib>=3.8
Requires-Dist: jinja2>=3.1
Requires-Dist: PyYAML>=6.0
Requires-Dist: sqlalchemy>=2.0
Requires-Dist: psycopg2-binary>=2.9
Requires-Dist: openai>=1.3
Requires-Dist: python-dotenv>=1.0
Requires-Dist: redis>=5.0
Requires-Dist: pyarrow>=10.0
Requires-Dist: pytest>=7.0
Provides-Extra: dev
Requires-Dist: pytest>=7.0; extra == "dev"
Requires-Dist: pytest-cov; extra == "dev"
Requires-Dist: black>=22.0.0; extra == "dev"
Requires-Dist: flake8; extra == "dev"
Requires-Dist: mypy; extra == "dev"
Requires-Dist: isort>=5.10.0; extra == "dev"
Provides-Extra: docs
Requires-Dist: sphinx; extra == "docs"
Requires-Dist: sphinx-rtd-theme; extra == "docs"
Provides-Extra: llm
Requires-Dist: langchain-core>=0.1; extra == "llm"
Requires-Dist: langchain-openai>=0.1; extra == "llm"
Dynamic: author
Dynamic: home-page
Dynamic: requires-python
